{
  "db_name": "PostgreSQL",
  "query": "\n        INSERT INTO users (email, username, password_hash, role, email_verified)\n        VALUES ($1, $2, $3, 'admin', true)\n        ON CONFLICT (email) DO UPDATE SET\n            role = 'admin',\n            email_verified = true,\n            password_hash = CASE WHEN $4 THEN EXCLUDED.password_hash ELSE users.password_hash END\n        RETURNING id, email, username, role\n        ",
  "describe": {
    "columns": [
      {
        "ordinal": 0,
        "name": "id",
        "type_info": "Uuid"
      },
      {
        "ordinal": 1,
        "name": "email",
        "type_info": {
          "Custom": {
            "name": "citext",
            "kind": "Simple"
          }
        }
      },
      {
        "ordinal": 2,
        "name": "username",
        "type_info": {
          "Custom": {
            "name": "citext",
            "kind": "Simple"
          }
        }
      },
      {
        "ordinal": 3,
        "name": "role",
        "type_info": "Text"
      }
    ],
    "parameters": {
      "Left": [
        {
          "Custom": {
            "name": "citext",
            "kind": "Simple"
          }
        },
        {
          "Custom": {
            "name": "citext",
            "kind": "Simple"
          }
        },
        "Text",
        "Bool"
      ]
    },
    "nullable": [
      false,
      false,
      false,
      false
    ]
  },
  "hash": "175d3a27bd60b18f28aec195373f23ea2342b4fc25d441e8de7f1dfb6fe348ec"
}
